opentoolshub/__init__.py
opentoolshub/add_two_numbers.py
opentoolshub/convert_binary_to_decimal.py
opentoolshub/convert_binary_to_hexadecimal.py
opentoolshub/convert_binary_to_octal.py
opentoolshub/convert_celsius_to_fahrenheit.py
opentoolshub/convert_centimeters_to_feet.py
opentoolshub/convert_centimeters_to_inches.py
opentoolshub/convert_days_to_hours.py
opentoolshub/convert_days_to_minutes.py
opentoolshub/convert_days_to_seconds.py
opentoolshub/convert_decimal_to_binary.py
opentoolshub/convert_decimal_to_hexadecimal.py
opentoolshub/convert_decimal_to_octal.py
opentoolshub/convert_hexadecimal_to_binary.py
opentoolshub/convert_hexadecimal_to_decimal.py
opentoolshub/convert_hexadecimal_to_octal.py
opentoolshub/convert_octal_to_binary.py
opentoolshub/convert_octal_to_decimal.py
opentoolshub/convert_octal_to_hexadecimal.py
opentoolshub/format_to_camelcase.py
opentoolshub/format_to_constantcase.py
opentoolshub/format_to_dotcase.py
opentoolshub/format_to_kebabcase.py
opentoolshub/format_to_pascalcase.py
opentoolshub/format_to_pathcase.py
opentoolshub/format_to_snakecase.py
opentoolshub/format_to_titlecase.py
opentoolshub/substract_two_numbers.py
opentoolshub-0.0.4.dist-info/METADATA
opentoolshub-0.0.4.dist-info/WHEEL
opentoolshub-0.0.4.dist-info/top_level.txt
opentoolshub-0.0.4.dist-info/RECORD
