Metadata-Version: 2.1
Name: opentoolshub
Version: 0.0.4
Summary: A collection of useful open source tools
Home-page: https://github.com/codinasion/open-tools
Author: Harsh Raj
Author-email: harshraj8843@gmail.com
License: UNKNOWN
Project-URL: Bug Tracker, https://github.com/codinasion/open-tools/issues
Platform: UNKNOWN
Classifier: Programming Language :: Python :: 3
Classifier: Programming Language :: Python :: 3.10
Classifier: Topic :: Software Development :: Libraries :: Python Modules
Classifier: License :: OSI Approved :: MIT License
Classifier: Operating System :: OS Independent
Requires-Python: >=3.10
